nAIme/__init__.py
nAIme/get_suggestion.py
nAIme/GRAFT/GRAFT_Create_Suggestions_for_Family_Trees_Graphs_Using_Ordering_Functions_for_package.py
nAIme/GRAFT/__init__.py
nAIme/GRAFT/RelevantFiles/RelevantFiles.zip
nAIme/GRAFT/RelevantFiles/__init__.py
nAIme/Phonetic/__init__.py
nAIme/Phonetic/phonetic_suggestion.py
nAIme/Phonetic/RelevantFiles/__init__.py
nAIme/Phonetic/RelevantFiles/wt_First_Name_phonetic_algorithm_codes.csv
nAIme/SpokenName2Vec/__init__.py
nAIme/SpokenName2Vec/name2mp3.py
nAIme/SpokenName2Vec/run_names_project_sound.py
nAIme/SpokenName2Vec/run_sound.py
nAIme/SpokenName2Vec/splitDir.py
nAIme/SpokenName2Vec/RelevantFiles/RelevantFiles.7z
nAIme/SpokenName2Vec/RelevantFiles/__init__.py
test/__init__.py
test/test_myfunctions.py
nAIme-0.0.1.dist-info/METADATA
nAIme-0.0.1.dist-info/WHEEL
nAIme-0.0.1.dist-info/top_level.txt
nAIme-0.0.1.dist-info/RECORD
